{
  "nodes": [
    {
      "id": "11183",
      "label": "\u53cb\u7ea6/\u8054\u60f3",
      "group": "\u516c\u53f8"
    },
    {
      "id": "39909",
      "label": "\u8054\u60f3",
      "group": "\u5de5\u4f5c\u7ecf\u5386"
    },
    {
      "id": "7614",
      "label": "\u8054\u60f3\u521b\u6295\u96c6\u56e2(\u4e50\u57fa\u91d1)",
      "group": "\u6295\u8d44\u673a\u6784"
    },
    {
      "id": "1579",
      "label": "\u4e2d\u56fd\u5317\u4eac\u6d77\u6dc0\u533a",
      "group": "\u57ce\u5e02"
    },
    {
      "id": "3393",
      "label": "\u6768\u5174\u5efa",
      "group": "\u521b\u6295\u4eba\u7269"
    },
    {
      "id": "3722",
      "label": "\u4e2d\u56fd\u4e0a\u6d77\u5f90\u6c47\u533a",
      "group": "\u57ce\u5e02"
    },
    {
      "id": "3915",
      "label": "\u6167\u7406\u8d22",
      "group": "\u516c\u53f8"
    },
    {
      "id": "5341",
      "label": "\u94c3\u7a7a\u6e38\u620f(\u94c3\u7a7a\u7f51\u7edc)",
      "group": "\u516c\u53f8"
    },
    {
      "id": "11310",
      "label": "\u4e2d\u56fd\u5317\u4eac\u897f\u57ce\u533a",
      "group": "\u57ce\u5e02"
    },
    {
      "id": "11871",
      "label": "LongData\u9f99\u9ed8\u5347\u79d1\u6280",
      "group": "\u516c\u53f8"
    },
    {
      "id": "12206",
      "label": "ZAKER\u624e\u5ba2/\u6dd8\u523b",
      "group": "\u516c\u53f8"
    },
    {
      "id": "12241",
      "label": "\u6797\u6d69",
      "group": "\u521b\u6295\u4eba\u7269"
    },
    {
      "id": "13008",
      "label": "\u58a8\u8f68\u8ff9",
      "group": "\u516c\u53f8"
    },
    {
      "id": "13726",
      "label": "StyleWe",
      "group": "\u516c\u53f8"
    },
    {
      "id": "13935",
      "label": "\u8461\u8404\u6e38\u620f\u5385/\u7231\u89c6\u6e38\u79d1\u6280",
      "group": "\u516c\u53f8"
    },
    {
      "id": "15482",
      "label": "Face++\u65f7\u89c6\u79d1\u6280",
      "group": "\u516c\u53f8"
    },
    {
      "id": "22039",
      "label": "Stylewe\u7ec6\u523b\u7f51\u7edc",
      "group": "\u516c\u53f8"
    },
    {
      "id": "23232",
      "label": "\u4e91\u9014\u817e",
      "group": "\u516c\u53f8"
    },
    {
      "id": "23602",
      "label": "\u8c1b\u542c\u79d1\u6280/NewWifi\u65b0\u8def\u7531",
      "group": "\u516c\u53f8"
    },
    {
      "id": "23673",
      "label": "\u7ea6\u8fd0\u52a8-\u9e1f\u5b69\u79d1\u6280",
      "group": "\u516c\u53f8"
    },
    {
      "id": "31709",
      "label": "\u94c1\u76ae\u4eba\u79d1\u6280TinmanArts",
      "group": "\u516c\u53f8"
    },
    {
      "id": "31997",
      "label": "\u4e25\u5e08\u4e66\u9662",
      "group": "\u516c\u53f8"
    },
    {
      "id": "34006",
      "label": "\u7231\u8c03\u7814",
      "group": "\u516c\u53f8"
    },
    {
      "id": "37121",
      "label": "\u4efb\u6e38\u7f51-\u679c\u8303\u521b\u60f3",
      "group": "\u516c\u53f8"
    },
    {
      "id": "37894",
      "label": "\u4e2d\u56fd\u5317\u4eac\u671d\u9633\u533a",
      "group": "\u57ce\u5e02"
    },
    {
      "id": "39757",
      "label": "Shopex\u5546\u6d3e\u7f51\u7edc",
      "group": "\u516c\u53f8"
    },
    {
      "id": "42743",
      "label": "Loorin\u70d9\u5370\u7f51/\u6570\u5b57\u70d9\u5370",
      "group": "\u516c\u53f8"
    },
    {
      "id": "44762",
      "label": "\u6768\u5174\u5efa",
      "group": "\u521b\u6295\u4eba\u7269"
    },
    {
      "id": "51691",
      "label": "\u8054\u60f3\u4e4b\u661f",
      "group": "\u6295\u8d44\u673a\u6784"
    },
    {
      "id": "54276",
      "label": "\u51fb\u97f3\u8033\u673a(\u6572\u6572\u79d1\u6280)",
      "group": "\u516c\u53f8"
    },
    {
      "id": "55389",
      "label": "\u767e\u6069\u767e-\u5929\u5929\u767e\u5206\u767e",
      "group": "\u516c\u53f8"
    },
    {
      "id": "59197",
      "label": "\u5411\u5b88\u519b",
      "group": "\u521b\u6295\u4eba\u7269"
    },
    {
      "id": "59374",
      "label": "\u4e2d\u56fd\u5317\u4eac\u4e1c\u57ce\u533a",
      "group": "\u57ce\u5e02"
    },
    {
      "id": "24141",
      "label": "\u9ea6\u4e50\u8d2d",
      "group": "\u516c\u53f8"
    },
    {
      "id": "56596",
      "label": "\u5916\u8d38\u7535\u5546",
      "group": "\u6807\u7b7e"
    },
    {
      "id": "36354",
      "label": "\u670d\u88c5\u670d\u9970",
      "group": "\u6807\u7b7e"
    },
    {
      "id": "20089",
      "label": "\u7535\u5b50\u5546\u52a1",
      "group": "\u9886\u57df"
    },
    {
      "id": "47890",
      "label": "\u8bbe\u8ba1\u5e08\u7535\u5546",
      "group": "\u6807\u7b7e"
    },
    {
      "id": "46011",
      "label": "\u7535\u5b50\u5546\u52a1",
      "group": "\u6807\u7b7e"
    },
    {
      "id": "45859",
      "label": "\u4e2d\u56fd\u5317\u4eac",
      "group": "\u7701\u4efd"
    },
    {
      "id": "22809",
      "label": "\u6d77\u5916\u5e02\u573a",
      "group": "\u6807\u7b7e"
    },
    {
      "id": "26231",
      "label": "\u5fae\u8f6f",
      "group": "\u5de5\u4f5c\u7ecf\u5386"
    },
    {
      "id": "27128",
      "label": "\u738b\u632f\u534e",
      "group": "\u521b\u6295\u4eba\u7269"
    },
    {
      "id": "44648",
      "label": "\u674e\u6170",
      "group": "\u521b\u6295\u4eba\u7269"
    },
    {
      "id": "18114",
      "label": "\u59da\u5316\u5316",
      "group": "\u521b\u6295\u4eba\u7269"
    },
    {
      "id": "19114",
      "label": "\u6f2b\u6b65\u5357\u9523\u9f13\u5df7/\u82f9\u5b89\u4e91\u4eab\u79d1\u6280",
      "group": "\u516c\u53f8"
    },
    {
      "id": "25735",
      "label": "O2O",
      "group": "\u6807\u7b7e"
    },
    {
      "id": "2434",
      "label": "\u5360\u51b0\u5f3a",
      "group": "\u521b\u6295\u4eba\u7269"
    },
    {
      "id": "5055",
      "label": "\u559c\u5b9d\u52a8\u529b/\u8d85\u7ea7\u8f66\u624b",
      "group": "\u516c\u53f8"
    },
    {
      "id": "7192",
      "label": "\u5f20\u7389\u56fd",
      "group": "\u521b\u6295\u4eba\u7269"
    },
    {
      "id": "9552",
      "label": "\u827e\u83b1\u65afAries",
      "group": "\u516c\u53f8"
    },
    {
      "id": "11093",
      "label": "\u98de\u6d41\u4e5d\u5929",
      "group": "\u516c\u53f8"
    },
    {
      "id": "12272",
      "label": "\u6768\u5149\u5b8f",
      "group": "\u521b\u6295\u4eba\u7269"
    },
    {
      "id": "13924",
      "label": "\u963f\u5c14\u6cd5\u516c\u793e",
      "group": "\u6295\u8d44\u673a\u6784"
    },
    {
      "id": "19654",
      "label": "\u7231\u601d\u552f\u5c14\u533b\u5b66\u7f51/\u7231\u552f\u533b\u5b66\u7f51",
      "group": "\u516c\u53f8"
    },
    {
      "id": "21912",
      "label": "DeanYu",
      "group": "\u521b\u6295\u4eba\u7269"
    },
    {
      "id": "22261",
      "label": "AlexFarfurnik",
      "group": "\u521b\u6295\u4eba\u7269"
    },
    {
      "id": "23118",
      "label": "Keep",
      "group": "\u516c\u53f8"
    },
    {
      "id": "25714",
      "label": "\u91d1\u7535\u8054\u884c",
      "group": "\u516c\u53f8"
    },
    {
      "id": "28739",
      "label": "\u67da\u5b50/\u638c\u4e0a\u4e91\u666f\u79d1\u6280",
      "group": "\u516c\u53f8"
    },
    {
      "id": "31804",
      "label": "\u848b\u4e9a\u840c",
      "group": "\u521b\u6295\u4eba\u7269"
    },
    {
      "id": "33432",
      "label": "\u8155\u6295",
      "group": "\u516c\u53f8"
    },
    {
      "id": "36836",
      "label": "\u9ec4\u78ca",
      "group": "\u521b\u6295\u4eba\u7269"
    },
    {
      "id": "39135",
      "label": "\u94b1\u4f1f",
      "group": "\u521b\u6295\u4eba\u7269"
    },
    {
      "id": "40804",
      "label": "\u827a\u8bc4\u7f51",
      "group": "\u516c\u53f8"
    },
    {
      "id": "41817",
      "label": "\u738b\u68b5\u6ed4",
      "group": "\u521b\u6295\u4eba\u7269"
    },
    {
      "id": "45011",
      "label": "\u4f18\u808c\u793e",
      "group": "\u516c\u53f8"
    },
    {
      "id": "45089",
      "label": "InfinityVenturePartners",
      "group": "\u6295\u8d44\u673a\u6784"
    },
    {
      "id": "45790",
      "label": "\u5965\u79d8\u57ce\u5e02",
      "group": "\u516c\u53f8"
    },
    {
      "id": "49489",
      "label": "\u80e1\u5b87\u7fd4",
      "group": "\u521b\u6295\u4eba\u7269"
    },
    {
      "id": "50162",
      "label": "\u4ed8\u7389\u73b2",
      "group": "\u521b\u6295\u4eba\u7269"
    },
    {
      "id": "50649",
      "label": "\u4fdd\u51c6\u725b",
      "group": "\u516c\u53f8"
    },
    {
      "id": "50857",
      "label": "\u6377\u62a5\u6307\u5411/wizad",
      "group": "\u516c\u53f8"
    },
    {
      "id": "52922",
      "label": "\u502a\u53bf\u4e50",
      "group": "\u521b\u6295\u4eba\u7269"
    },
    {
      "id": "54332",
      "label": "\u9648\u777f",
      "group": "\u521b\u6295\u4eba\u7269"
    },
    {
      "id": "54506",
      "label": "\u5c39\u96ea",
      "group": "\u521b\u6295\u4eba\u7269"
    },
    {
      "id": "54547",
      "label": "\u7f8e\u56fd\u4e2d\u7ecf\u5408\u96c6\u56e2",
      "group": "\u6295\u8d44\u673a\u6784"
    },
    {
      "id": "19709",
      "label": "\u9648\u6f47\u67ab",
      "group": "\u521b\u6295\u4eba\u7269"
    }
  ],
  "edges": [
    {
      "from": "59197",
      "to": "3722",
      "label": "\u5c45\u4f4f\u4e8e"
    },
    {
      "from": "7614",
      "to": "23673",
      "label": "\u6295\u8d44"
    },
    {
      "from": "7614",
      "to": "13726",
      "label": "\u6295\u8d44"
    },
    {
      "from": "7614",
      "to": "23602",
      "label": "\u6295\u8d44"
    },
    {
      "from": "12241",
      "to": "1579",
      "label": "\u5c45\u4f4f\u4e8e"
    },
    {
      "from": "7614",
      "to": "34006",
      "label": "\u6295\u8d44"
    },
    {
      "from": "7614",
      "to": "12206",
      "label": "\u6295\u8d44"
    },
    {
      "from": "54276",
      "to": "1579",
      "label": "\u4f4d\u4e8e\uff08\u57ce\u5e02\uff09"
    },
    {
      "from": "23232",
      "to": "1579",
      "label": "\u4f4d\u4e8e\uff08\u57ce\u5e02\uff09"
    },
    {
      "from": "7614",
      "to": "15482",
      "label": "\u6295\u8d44"
    },
    {
      "from": "7614",
      "to": "23602",
      "label": "\u6295\u8d44"
    },
    {
      "from": "7614",
      "to": "22039",
      "label": "\u6295\u8d44"
    },
    {
      "from": "7614",
      "to": "13935",
      "label": "\u6295\u8d44"
    },
    {
      "from": "7614",
      "to": "23232",
      "label": "\u6295\u8d44"
    },
    {
      "from": "51691",
      "to": "31709",
      "label": "\u6295\u8d44"
    },
    {
      "from": "7614",
      "to": "54276",
      "label": "\u6295\u8d44"
    },
    {
      "from": "7614",
      "to": "31997",
      "label": "\u6295\u8d44"
    },
    {
      "from": "7614",
      "to": "37121",
      "label": "\u6295\u8d44"
    },
    {
      "from": "7614",
      "to": "55389",
      "label": "\u6295\u8d44"
    },
    {
      "from": "15482",
      "to": "1579",
      "label": "\u4f4d\u4e8e\uff08\u57ce\u5e02\uff09"
    },
    {
      "from": "7614",
      "to": "3915",
      "label": "\u6295\u8d44"
    },
    {
      "from": "7614",
      "to": "11871",
      "label": "\u6295\u8d44"
    },
    {
      "from": "7614",
      "to": "13008",
      "label": "\u6295\u8d44"
    },
    {
      "from": "7614",
      "to": "31709",
      "label": "\u6295\u8d44"
    },
    {
      "from": "22039",
      "to": "37894",
      "label": "\u4f4d\u4e8e\uff08\u57ce\u5e02\uff09"
    },
    {
      "from": "55389",
      "to": "37894",
      "label": "\u4f4d\u4e8e\uff08\u57ce\u5e02\uff09"
    },
    {
      "from": "7614",
      "to": "42743",
      "label": "\u6295\u8d44"
    },
    {
      "from": "51691",
      "to": "34006",
      "label": "\u6295\u8d44"
    },
    {
      "from": "44762",
      "to": "37894",
      "label": "\u5c45\u4f4f\u4e8e"
    },
    {
      "from": "34006",
      "to": "3722",
      "label": "\u4f4d\u4e8e\uff08\u57ce\u5e02\uff09"
    },
    {
      "from": "7614",
      "to": "39757",
      "label": "\u6295\u8d44"
    },
    {
      "from": "7614",
      "to": "5341",
      "label": "\u6295\u8d44"
    },
    {
      "from": "12241",
      "to": "39909",
      "label": "\u66fe\u5c31\u804c\u4e8e"
    },
    {
      "from": "7614",
      "to": "37121",
      "label": "\u6295\u8d44"
    },
    {
      "from": "31997",
      "to": "11310",
      "label": "\u4f4d\u4e8e\uff08\u57ce\u5e02\uff09"
    },
    {
      "from": "51691",
      "to": "12206",
      "label": "\u6295\u8d44"
    },
    {
      "from": "13008",
      "to": "1579",
      "label": "\u4f4d\u4e8e\uff08\u57ce\u5e02\uff09"
    },
    {
      "from": "44762",
      "to": "22039",
      "label": "\u6210\u5458"
    },
    {
      "from": "13935",
      "to": "1579",
      "label": "\u4f4d\u4e8e\uff08\u57ce\u5e02\uff09"
    },
    {
      "from": "12241",
      "to": "54276",
      "label": "\u6210\u5458"
    },
    {
      "from": "11183",
      "to": "1579",
      "label": "\u4f4d\u4e8e\uff08\u57ce\u5e02\uff09"
    },
    {
      "from": "13726",
      "to": "59374",
      "label": "\u4f4d\u4e8e\uff08\u57ce\u5e02\uff09"
    },
    {
      "from": "39757",
      "to": "3722",
      "label": "\u4f4d\u4e8e\uff08\u57ce\u5e02\uff09"
    },
    {
      "from": "51691",
      "to": "15482",
      "label": "\u6295\u8d44"
    },
    {
      "from": "59197",
      "to": "34006",
      "label": "\u6210\u5458"
    },
    {
      "from": "11871",
      "to": "3722",
      "label": "\u4f4d\u4e8e\uff08\u57ce\u5e02\uff09"
    },
    {
      "from": "42743",
      "to": "1579",
      "label": "\u4f4d\u4e8e\uff08\u57ce\u5e02\uff09"
    },
    {
      "from": "3393",
      "to": "13726",
      "label": "\u6210\u5458"
    },
    {
      "from": "22039",
      "to": "56596",
      "label": "\u6807\u7b7e"
    },
    {
      "from": "24141",
      "to": "56596",
      "label": "\u6807\u7b7e"
    },
    {
      "from": "24141",
      "to": "59374",
      "label": "\u4f4d\u4e8e\uff08\u57ce\u5e02\uff09"
    },
    {
      "from": "13726",
      "to": "36354",
      "label": "\u6807\u7b7e"
    },
    {
      "from": "22039",
      "to": "36354",
      "label": "\u6807\u7b7e"
    },
    {
      "from": "24141",
      "to": "20089",
      "label": "\u9886\u57df"
    },
    {
      "from": "22039",
      "to": "20089",
      "label": "\u9886\u57df"
    },
    {
      "from": "22039",
      "to": "47890",
      "label": "\u6807\u7b7e"
    },
    {
      "from": "13726",
      "to": "47890",
      "label": "\u6807\u7b7e"
    },
    {
      "from": "13726",
      "to": "46011",
      "label": "\u6807\u7b7e"
    },
    {
      "from": "22039",
      "to": "46011",
      "label": "\u6807\u7b7e"
    },
    {
      "from": "13726",
      "to": "20089",
      "label": "\u9886\u57df"
    },
    {
      "from": "59374",
      "to": "45859",
      "label": "\u5c5e\u4e8e"
    },
    {
      "from": "37894",
      "to": "45859",
      "label": "\u5c5e\u4e8e"
    },
    {
      "from": "22039",
      "to": "22809",
      "label": "\u6807\u7b7e"
    },
    {
      "from": "13726",
      "to": "22809",
      "label": "\u6807\u7b7e"
    },
    {
      "from": "27128",
      "to": "26231",
      "label": "\u66fe\u5c31\u804c\u4e8e"
    },
    {
      "from": "59197",
      "to": "26231",
      "label": "\u66fe\u5c31\u804c\u4e8e"
    },
    {
      "from": "27128",
      "to": "59374",
      "label": "\u5c45\u4f4f\u4e8e"
    },
    {
      "from": "44648",
      "to": "26231",
      "label": "\u66fe\u5c31\u804c\u4e8e"
    },
    {
      "from": "44648",
      "to": "59374",
      "label": "\u5c45\u4f4f\u4e8e"
    },
    {
      "from": "18114",
      "to": "26231",
      "label": "\u66fe\u5c31\u804c\u4e8e"
    },
    {
      "from": "18114",
      "to": "59374",
      "label": "\u5c45\u4f4f\u4e8e"
    },
    {
      "from": "19114",
      "to": "25735",
      "label": "\u6807\u7b7e"
    },
    {
      "from": "13008",
      "to": "25735",
      "label": "\u6807\u7b7e"
    },
    {
      "from": "19114",
      "to": "59374",
      "label": "\u4f4d\u4e8e\uff08\u57ce\u5e02\uff09"
    },
    {
      "from": "49489",
      "to": "59374",
      "label": "\u5c45\u4f4f\u4e8e"
    },
    {
      "from": "19654",
      "to": "59374",
      "label": "\u4f4d\u4e8e\uff08\u57ce\u5e02\uff09"
    },
    {
      "from": "31804",
      "to": "59374",
      "label": "\u5c45\u4f4f\u4e8e"
    },
    {
      "from": "28739",
      "to": "59374",
      "label": "\u4f4d\u4e8e\uff08\u57ce\u5e02\uff09"
    },
    {
      "from": "52922",
      "to": "59374",
      "label": "\u5c45\u4f4f\u4e8e"
    },
    {
      "from": "5055",
      "to": "59374",
      "label": "\u4f4d\u4e8e\uff08\u57ce\u5e02\uff09"
    },
    {
      "from": "45011",
      "to": "59374",
      "label": "\u4f4d\u4e8e\uff08\u57ce\u5e02\uff09"
    },
    {
      "from": "40804",
      "to": "59374",
      "label": "\u4f4d\u4e8e\uff08\u57ce\u5e02\uff09"
    },
    {
      "from": "50857",
      "to": "59374",
      "label": "\u4f4d\u4e8e\uff08\u57ce\u5e02\uff09"
    },
    {
      "from": "33432",
      "to": "59374",
      "label": "\u4f4d\u4e8e\uff08\u57ce\u5e02\uff09"
    },
    {
      "from": "54332",
      "to": "59374",
      "label": "\u5c45\u4f4f\u4e8e"
    },
    {
      "from": "39135",
      "to": "59374",
      "label": "\u5c45\u4f4f\u4e8e"
    },
    {
      "from": "2434",
      "to": "59374",
      "label": "\u5c45\u4f4f\u4e8e"
    },
    {
      "from": "25714",
      "to": "59374",
      "label": "\u4f4d\u4e8e\uff08\u57ce\u5e02\uff09"
    },
    {
      "from": "54506",
      "to": "59374",
      "label": "\u5c45\u4f4f\u4e8e"
    },
    {
      "from": "9552",
      "to": "59374",
      "label": "\u4f4d\u4e8e\uff08\u57ce\u5e02\uff09"
    },
    {
      "from": "21912",
      "to": "59374",
      "label": "\u5c45\u4f4f\u4e8e"
    },
    {
      "from": "36836",
      "to": "59374",
      "label": "\u5c45\u4f4f\u4e8e"
    },
    {
      "from": "50649",
      "to": "59374",
      "label": "\u4f4d\u4e8e\uff08\u57ce\u5e02\uff09"
    },
    {
      "from": "22261",
      "to": "5055",
      "label": "\u6210\u5458"
    },
    {
      "from": "31804",
      "to": "54547",
      "label": "\u6210\u5458"
    },
    {
      "from": "11093",
      "to": "59374",
      "label": "\u4f4d\u4e8e\uff08\u57ce\u5e02\uff09"
    },
    {
      "from": "7192",
      "to": "19654",
      "label": "\u6210\u5458"
    },
    {
      "from": "28739",
      "to": "46011",
      "label": "\u6807\u7b7e"
    },
    {
      "from": "45790",
      "to": "25735",
      "label": "\u6807\u7b7e"
    },
    {
      "from": "45790",
      "to": "59374",
      "label": "\u4f4d\u4e8e\uff08\u57ce\u5e02\uff09"
    },
    {
      "from": "12272",
      "to": "59374",
      "label": "\u5c45\u4f4f\u4e8e"
    },
    {
      "from": "41817",
      "to": "5055",
      "label": "\u6210\u5458"
    },
    {
      "from": "45089",
      "to": "5055",
      "label": "\u6295\u8d44"
    },
    {
      "from": "49489",
      "to": "45790",
      "label": "\u6210\u5458"
    },
    {
      "from": "5055",
      "to": "20089",
      "label": "\u9886\u57df"
    },
    {
      "from": "52922",
      "to": "39909",
      "label": "\u66fe\u5c31\u804c\u4e8e"
    },
    {
      "from": "22261",
      "to": "59374",
      "label": "\u5c45\u4f4f\u4e8e"
    },
    {
      "from": "50162",
      "to": "28739",
      "label": "\u6210\u5458"
    },
    {
      "from": "45011",
      "to": "46011",
      "label": "\u6807\u7b7e"
    },
    {
      "from": "7192",
      "to": "37894",
      "label": "\u5c45\u4f4f\u4e8e"
    },
    {
      "from": "41817",
      "to": "59374",
      "label": "\u5c45\u4f4f\u4e8e"
    },
    {
      "from": "28739",
      "to": "20089",
      "label": "\u9886\u57df"
    },
    {
      "from": "31804",
      "to": "13924",
      "label": "\u6210\u5458"
    },
    {
      "from": "12272",
      "to": "5055",
      "label": "\u6210\u5458"
    },
    {
      "from": "45011",
      "to": "20089",
      "label": "\u9886\u57df"
    },
    {
      "from": "52922",
      "to": "11093",
      "label": "\u6210\u5458"
    },
    {
      "from": "5055",
      "to": "46011",
      "label": "\u6807\u7b7e"
    },
    {
      "from": "50162",
      "to": "59374",
      "label": "\u5c45\u4f4f\u4e8e"
    },
    {
      "from": "19709",
      "to": "12206",
      "label": "\u6210\u5458"
    },
    {
      "from": "19709",
      "to": "59374",
      "label": "\u5c45\u4f4f\u4e8e"
    },
    {
      "from": "23118",
      "to": "59374",
      "label": "\u4f4d\u4e8e\uff08\u57ce\u5e02\uff09"
    },
    {
      "from": "3393",
      "to": "59374",
      "label": "\u5c45\u4f4f\u4e8e"
    }
  ]
}